Metadata-Version: 2.1
Name: objfunc
Version: 0.0.1.dev1
Summary: Client for objfunc.com
Home-page: https://github.com/azurelysium/objfunc-cli
Author: Minhwan Kim
Author-email: minhwan.kim@member.fsf.org
License: UNKNOWN
Project-URL: Documentation, https://github.com/azurelysium/objfunc-cli
Project-URL: Source Code, https://github.com/azurelysium/objfunc-cli
Keywords: client API
Platform: UNKNOWN
Classifier: License :: OSI Approved :: MIT License
Requires-Python: >=3.*
